DLBI/__init__.py
DLBI/bi2.py
DLBI/bi5.py
DLBI/bi6.py
DLBI/dl1.py
DLBI/dl2.py
DLBI/dl3.py
DLBI/dl4.py
DLBI/dl4n.py
DLBI/dl5.py
DL_BI/__init__.py
DL_BI/bi2.py
DL_BI/bi5.py
DL_BI/bi6.py
DL_BI/dl1.py
DL_BI/dl2.py
DL_BI/dl3.py
DL_BI/dl4.py
DL_BI/dl4n.py
DL_BI/dl5.py
DL_BIp-0.1.dist-info/METADATA
DL_BIp-0.1.dist-info/WHEEL
DL_BIp-0.1.dist-info/top_level.txt
DL_BIp-0.1.dist-info/RECORD
